protein_design/__init__.py
protein_design/constants.py
protein_design/data.py
protein_design/discriminative.py
protein_design/evaluator.py
protein_design/generative.py
protein_design/learning.py
protein_design/sequence.py
protein_design/splitter.py
protein_design/structure.py
protein_design/trainer.py
protein_design-1.0.2.dist-info/LICENSE
protein_design-1.0.2.dist-info/WHEEL
protein_design-1.0.2.dist-info/METADATA
protein_design-1.0.2.dist-info/RECORD
